recforest/__init__.py
recforest/_transform.cp37-win_amd64.pyd
recforest/model.py
recforest/setup.py
recforest/utils.py
RecForest-0.1.0.dist-info/LICENSE
RecForest-0.1.0.dist-info/METADATA
RecForest-0.1.0.dist-info/WHEEL
RecForest-0.1.0.dist-info/top_level.txt
RecForest-0.1.0.dist-info/RECORD
