Metadata-Version: 2.1
Name: RecForest
Version: 0.1.0
Summary: Implementation of Reconstruction-based Anomaly Detection with Completely Random Forest
Home-page: https://github.com/xuyxu/RecForest
Maintainer: Yi-Xuan Xu
Maintainer-email: xuyx@lamda.nju.edu.cn
License: BSD 3-Clause
Project-URL: Bug Tracker, https://github.com/xuyxu/RecForest/issues
Project-URL: Documentation, https://github.com/xuyxu/RecForest/README.rst
Project-URL: Source Code, https://github.com/xuyxu/RecForest
Keywords: Anomaly Detection,Decition Tree Ensemble
Platform: UNKNOWN
Classifier: Intended Audience :: Science/Research
Classifier: Intended Audience :: Developers
Classifier: Topic :: Software Development
Classifier: Topic :: Scientific/Engineering
Classifier: Operating System :: Microsoft :: Windows
Classifier: Operating System :: POSIX
Classifier: Operating System :: Unix
Classifier: Programming Language :: Python :: 3
Classifier: Programming Language :: Python :: 3.6
Classifier: Programming Language :: Python :: 3.7
Classifier: Programming Language :: Python :: 3.8
Requires-Python: >=3.6
Requires-Dist: numpy (>=1.13.3)
Requires-Dist: scipy (>=0.19.1)
Requires-Dist: joblib (>=0.12)
Requires-Dist: cython (>=0.28.5)
Requires-Dist: scikit-learn (>=0.22)
